numrs/__init__.py
numrs/__init__.pyi
numrs/array.py
numrs/native_lib.py
numrs/native_lib.pyi
numrs/nn.py
numrs/onnx.py
numrs/py.typed
numrs/tensor.py
numrs/train.py
numrs/train.pyi
numrs/types.py
numrs-0.1.23.dist-info/METADATA
numrs-0.1.23.dist-info/WHEEL
numrs-0.1.23.dist-info/top_level.txt
numrs-0.1.23.dist-info/RECORD
