Metadata-Version: 2.1
Name: numrs
Version: 0.1.23
Summary: Python bindings for NumRs
License: AGPL-3.0-only
Requires-Python: >=3.7
Requires-Dist: typing-extensions ; python_version < "3.8"
